README.md
setup.py
sejings/__init__.py
sejings/__version__.py
sejings/core.py
sejings/decorator.py
sejings/utils.py
sejings.egg-info/PKG-INFO
sejings.egg-info/SOURCES.txt
sejings.egg-info/dependency_links.txt
sejings.egg-info/top_level.txt