Metadata-Version: 2.1
Name: sejings
Version: 0.0.2
Summary: A simple package for rapidly developing system settings.
Home-page: https://github.com/EmilianoJordan/Sejings
Author: Emiliano Jordan
Author-email: emiliano.jordan+sejings@protonmail.com
License: Apache License 2.0
Project-URL: Source, https://github.com/EmilianoJordan/Settings/
Project-URL: Tracker, https://github.com/EmilianoJordan/Settings/issues
Platform: UNKNOWN
Classifier: Programming Language :: Python
Classifier: Programming Language :: Python :: 3
Classifier: Programming Language :: Python :: 3.6
Classifier: Programming Language :: Python :: 3.7
Classifier: Programming Language :: Python :: 3.8
Classifier: Topic :: Software Development :: Libraries :: Python Modules
Classifier: Topic :: Utilities
